automation_direct_stock/__init__.py
automation_direct_stock/__main__.py
automation_direct_stock/checker.py
automation_direct_stock-1.0.0.data/scripts/adstock
automation_direct_stock-1.0.0.dist-info/METADATA
automation_direct_stock-1.0.0.dist-info/RECORD
automation_direct_stock-1.0.0.dist-info/WHEEL
automation_direct_stock-1.0.0.dist-info/top_level.txt
