Metadata-Version: 2.1
Name: automation-direct-stock
Version: 1.0.0
Summary: package checks Automation Direct's products' availability
Home-page: https://github.com/PhilipConte/automation_direct_stock
Author: Philip Conte
Author-email: philipmconte@gmail.com
License: MIT
Download-URL: https://github.com/PhilipConte/automation_direct_stock/archive/1.0.0.tar.gz
Keywords: automation direct stock
Platform: UNKNOWN
Classifier: Programming Language :: Python :: 3
Classifier: License :: OSI Approved :: MIT License
Classifier: Operating System :: OS Independent
Requires-Dist: requests
Requires-Dist: beautifulsoup4
